{
    "minTemperature": 25,
    "maxTemperature": 35,
    "temperatureConfigs": [],
    "humidityConfigs": [],
    "soilMoistureConfigs": [{
        "greenHouseId": 789456123,
        "minSoilMoisture": 30,
        "maxSoilMoisture": 55
    }],
    "minHumidity": 50,
    "maxHumidity": 70,
    "fertilityConfigs": [{
        "projectId": 2,
        "minFertility": 30,
        "maxFertility": 50
    }, {
        "projectId": 1,
        "minFertility": 50,
        "maxFertility": 70
    }, {
        "projectId": 3,
        "minFertility": 30,
        "maxFertility": 70
    }],
    "minAmbientLight": null,
    "maxAmbientLight": null,
    "minSoilMoisture": 30,
    "maxSoilMoisture": 40,
    "watering": [{
        "greenHouseId": 789456120,
        "timeRanges": []
    }],
    "fertilizer": []
}